rubric/__init__.py
pymdown_rubric_extension-0.1.1.dist-info/METADATA
pymdown_rubric_extension-0.1.1.dist-info/WHEEL
pymdown_rubric_extension-0.1.1.dist-info/RECORD
